cotyBot/__init__.py
cotyBot/cotyBotConsole.py
cotyBot-0.0.1.dist-info/LICENSE
cotyBot-0.0.1.dist-info/METADATA
cotyBot-0.0.1.dist-info/WHEEL
cotyBot-0.0.1.dist-info/entry_points.txt
cotyBot-0.0.1.dist-info/top_level.txt
cotyBot-0.0.1.dist-info/RECORD
