Metadata-Version: 2.1
Name: cotyBot
Version: 0.0.1
Summary: 捏一个替我完成重复性工作的机器人，就叫 Coty 吧。
Home-page: https://gitee.com/catcat7/coty-bot
Author: chenjiancheng
Author-email: quinn.7@foxmail.com
Keywords: python,testing,automation,coty,coty-bot,CotyBot
Classifier: Programming Language :: Python :: 3.10
License-File: LICENSE
Requires-Dist: playwright
Requires-Dist: flask
Requires-Dist: websockets-routes
